evenoddchecker/check.py
evenoddchecker/init.py
evenoddchecker-0.1.0.dist-info/METADATA
evenoddchecker-0.1.0.dist-info/WHEEL
evenoddchecker-0.1.0.dist-info/top_level.txt
evenoddchecker-0.1.0.dist-info/RECORD
