Metadata-Version: 2.4
Name: evenoddchecker
Version: 0.1.0
Summary: A simple Python package to check odd or even numbers
Author-email: Your Name <you@example.com>
License: MIT
Project-URL: homepage, https://github.com/yourusername/evenoddchecker
Requires-Python: >=3.7
